twitter_analytics/downloader.py
twitter_analytics/utils.py
twitter_analytics/calendar.py
twitter_analytics/__init__.py
twitter_analytics-1.0.dist-info/DESCRIPTION.rst
twitter_analytics-1.0.dist-info/top_level.txt
twitter_analytics-1.0.dist-info/RECORD
twitter_analytics-1.0.dist-info/METADATA
twitter_analytics-1.0.dist-info/WHEEL
twitter_analytics-1.0.dist-info/metadata.json
