Metadata-Version: 2.0
Name: twitter-analytics
Version: 1.0
Summary: A twitter analytics reports downloader. The only way to get tweet impressions data with Python
Home-page: https://github.com/philippe2803/twitter-analytics-wrapper
Author: Philippe Oger
Author-email: phil.oger@gmail.com
License: MIT
Keywords: twitter analytics reports downloader
Platform: UNKNOWN
Classifier: Development Status :: 3 - Alpha
Classifier: Environment :: Web Environment
Classifier: Intended Audience :: Developers
Classifier: Operating System :: POSIX :: Linux
Classifier: Programming Language :: Python
Classifier: Programming Language :: Python :: 2
Classifier: Programming Language :: Python :: 2.7
Classifier: Programming Language :: Python :: 3
Classifier: Programming Language :: Python :: 3.3
Classifier: Programming Language :: Python :: 3.4
Classifier: Programming Language :: Python :: 3.5
Classifier: Programming Language :: Python :: 3.6
Classifier: Topic :: Software Development :: Libraries :: Python Modules
Requires-Dist: selenium
Requires-Dist: python-dateutil
Requires-Dist: pyvirtualdisplay
